pyncov/__init__.py
pyncov/data/__init__.py
pyncov/data/iso-codes.csv
pyncov/data/population.csv
pyncov/datasets.py
pyncov/io.py
pyncov/plot.py
pyncov/pyncov.py
pyncov-0.1.6.dist-info/LICENSE
pyncov-0.1.6.dist-info/WHEEL
pyncov-0.1.6.dist-info/METADATA
pyncov-0.1.6.dist-info/RECORD
