Metadata-Version: 2.1
Name: pyncov
Version: 0.1.6
Summary: Pyncov-19 is a tiny probabilistic simulator for SARS-CoV-2
Home-page: https://github.com/covid19-modeling/pyncov-19
License: MIT
Author: Pablo R. Mier
Author-email: pablo.rodriguez-mier@inrae.fr
Requires-Python: >=3.6.1,<4.0.0
Classifier: Development Status :: 5 - Production/Stable
Classifier: Intended Audience :: Science/Research
Classifier: License :: OSI Approved :: MIT License
Classifier: Natural Language :: English
Classifier: Programming Language :: Python :: 3
Classifier: Programming Language :: Python :: 3.7
Classifier: Programming Language :: Python :: 3.8
Classifier: Programming Language :: Python :: 3.9
Classifier: Topic :: Scientific/Engineering :: Mathematics
Provides-Extra: all
Requires-Dist: matplotlib (>=3.2.1,<4.0.0); extra == "all"
Requires-Dist: numpy (>=1.18.1,<2.0.0)
Requires-Dist: pandas (>=1.0.0,<2.0.0); extra == "all"
Requires-Dist: tqdm (>=4.41.0,<5.0.0); extra == "all"
Project-URL: Repository, https://github.com/covid19-modeling/pyncov-19
